LICENSE.md
README.md
setup.py
eiq/__init__.py
eiq/config.py
eiq/utils.py
eiq/apps/__init__.py
eiq/apps/utils.py
eiq/apps/pyeiq_launcher/__init__.py
eiq/apps/pyeiq_launcher/config.py
eiq/apps/pyeiq_launcher/pyeiq.py
eiq/apps/switch_image/__init__.py
eiq/apps/switch_image/config.py
eiq/apps/switch_image/switch_image.py
eiq/apps/switch_video/__init__.py
eiq/apps/switch_video/config.py
eiq/apps/switch_video/switch_video.py
eiq/engines/__init__.py
eiq/engines/armnn/__init__.py
eiq/engines/armnn/inference.py
eiq/engines/opencv/__init__.py
eiq/engines/opencv/inference.py
eiq/engines/tflite/__init__.py
eiq/engines/tflite/inference.py
eiq/helper/__init__.py
eiq/helper/google_drive_downloader.py
eiq/modules/__init__.py
eiq/modules/utils.py
eiq/modules/classification/__init__.py
eiq/modules/classification/classification_armnn.py
eiq/modules/classification/classification_tflite.py
eiq/modules/classification/config.py
eiq/modules/detection/__init__.py
eiq/modules/detection/config.py
eiq/modules/detection/covid19_detection.py
eiq/modules/detection/facial_detection.py
eiq/modules/detection/object_detection_ssd.py
eiq/multimedia/__init__.py
eiq/multimedia/gstreamer.py
eiq/multimedia/overlay.py
eiq/multimedia/utils.py
eiq/multimedia/v4l2.py
pyeiq.egg-info/PKG-INFO
pyeiq.egg-info/SOURCES.txt
pyeiq.egg-info/dependency_links.txt
pyeiq.egg-info/not-zip-safe
pyeiq.egg-info/requires.txt
pyeiq.egg-info/top_level.txt