Metadata-Version: 2.1
Name: pyeiq
Version: 3.0.1
Summary: A Python Framework for eIQ on i.MX Processors
Home-page: https://source.codeaurora.org/external/imxsupport/pyeiq/
Author: Alifer Moraes, Diego Dorta, Marco Franchi, Kaixin Ding, Gnar Fang, Michael Pontikes, Jinghui Liu, Manish Bajaj, Devin Jiao
License: BSD-3-Clause
Keywords: ml,eiq,demos,apps
Platform: UNKNOWN
Classifier: Development Status :: 3 - Alpha
Classifier: Intended Audience :: Information Technology
Classifier: Natural Language :: English
Classifier: Operating System :: Other OS
Classifier: Programming Language :: Python :: 3.9
License-File: LICENSE.md
